{"v":"5.0.1","fr":10,"ip":0,"op":20,"w":52,"h":48,"assets":[],"layers":[{"ind":1,"nm":"Layer 1","ks":{"p":{"a":0,"k":[26,24]},"a":{"a":0,"k":[26,24,0]},"s":{"a":1,"k":[{"t":0,"s":[95,95,100],"i":{"x":[0.58],"y":[1]},"o":{"x":[0.42],"y":[0]},"e":[110,110.027,100]},{"t":12,"s":[110,110.027,100],"i":{"x":[0.58],"y":[1]},"o":{"x":[0.42],"y":[0]},"e":[95,95,100]},{"t":20,"s":[95,95,100]}]},"r":{"a":0,"k":0},"o":{"a":0,"k":100}},"ao":0,"ip":0,"op":20,"st":0,"bm":0,"sr":1,"ty":4,"shapes":[{"ty":"gr","it":[{"ty":"sh","d":1,"ks":{"a":0,"k":{"i":[[0,0],[0,9.424],[-7.178,0],[-1.972,-2.964],[-4.099,0],[0,-7.831],[12.473,-7.964],[0.465,0],[0.465,0.288]],"o":[[-12.496,-7.964],[0,-7.831],[4.099,0],[2.016,-2.986],[7.178,0],[0,9.424],[-0.487,0.288],[-0.465,0],[0,0]],"v":[[20.405,40.018],[0,13.361],[12.562,0],[22,4.933],[31.438,0],[44,13.361],[23.617,40.018],[22,40.615],[20.405,40.018]],"c":true},"hd":false}},{"ty":"fl","c":{"a":0,"k":[0.824,0.337,0.337,1]},"hd":false,"o":{"a":0,"k":100},"r":1},{"ty":"tr","p":{"a":0,"k":[30,27.692]},"a":{"a":0,"k":[26,24]},"s":{"a":0,"k":[100,100]},"r":{"a":0,"k":0},"o":{"a":0,"k":100},"sk":{"a":0,"k":0},"sa":{"a":0,"k":0}}],"nm":"Object","hd":false}]}]}